DycreatorDataCollection/__init__.py
DycreatorDataCollection/_dict.py
DycreatorDataCollection/_login.py
DycreatorDataCollection/_types.py
DycreatorDataCollection/_utils.py
DycreatorDataCollection/collector.py
DycreatorDataCollection/content/_dict.py
DycreatorDataCollection/content/_types.py
DycreatorDataCollection/content/content.py
DycreatorDataCollection/content/works.py
DycreatorDataCollection/data/_dict.py
DycreatorDataCollection/data/_types.py
DycreatorDataCollection/data/content.py
DycreatorDataCollection/data/data.py
dycreator_data_collection-1.0.17.dist-info/LICENSE
dycreator_data_collection-1.0.17.dist-info/METADATA
dycreator_data_collection-1.0.17.dist-info/WHEEL
dycreator_data_collection-1.0.17.dist-info/RECORD
